clemont/__init__.py
clemont/runner.py
clemont/backends/__init__.py
clemont/backends/base.py
clemont/backends/bdd.py
clemont/backends/discretization.py
clemont/backends/faiss.py
clemont/backends/kdtree.py
clemont/backends/snn.py
clemont-0.1.0.dist-info/licenses/LICENSE.txt
clemont-0.1.0.dist-info/METADATA
clemont-0.1.0.dist-info/WHEEL
clemont-0.1.0.dist-info/top_level.txt
clemont-0.1.0.dist-info/RECORD
