Metadata-Version: 2.4
Name: clemont
Version: 0.1.0
Summary: Monitoring AI models for fairness and robustness
Author-email: David Pape <david.pape@stud.plus.ac.at>
Project-URL: Homepage, https://github.com/ariez-xyz/clemont
Classifier: Development Status :: 3 - Alpha
Classifier: Intended Audience :: Developers
Classifier: License :: OSI Approved :: MIT License
Classifier: Operating System :: OS Independent
Classifier: Programming Language :: Python :: 3
Classifier: Programming Language :: Python :: 3.11
Classifier: Programming Language :: Python :: 3.12
Classifier: Programming Language :: Python :: 3.13
Requires-Python: >=3.11
License-File: LICENSE.txt
Requires-Dist: numpy
Requires-Dist: pandas
Requires-Dist: scikit-learn
Requires-Dist: faiss-cpu
Requires-Dist: psutil
Requires-Dist: snnpy==0.0.6
Dynamic: license-file
